deepqt/__init__.py
deepqt/api_interface.py
deepqt/config.py
deepqt/driver_api_config.py
deepqt/driver_epub_preview.py
deepqt/driver_mainwindow.py
deepqt/driver_text_preview.py
deepqt/file_table.py
deepqt/glossary.py
deepqt/helpers.py
deepqt/main.py
deepqt/quote_protection.py
deepqt/structures.py
deepqt/term_extractor.py
deepqt/trie.py
deepqt/worker_thread.py
deepqt/xml_parser.py
deepqt/CustomQ/CComboBox.py
deepqt/CustomQ/CTableWidget.py
deepqt/CustomQ/__init__.py
deepqt/rc_generated_files/__init__.py
deepqt/rc_generated_files/fallback_icons_rc.py
deepqt/ui_generated_files/__init__.py
deepqt/ui_generated_files/ui_api_config.py
deepqt/ui_generated_files/ui_epub_preview.py
deepqt/ui_generated_files/ui_mainwindow.py
deepqt/ui_generated_files/ui_text_preview.py
deepqt-1.1.7.dist-info/LICENSE
deepqt-1.1.7.dist-info/METADATA
deepqt-1.1.7.dist-info/WHEEL
deepqt-1.1.7.dist-info/entry_points.txt
deepqt-1.1.7.dist-info/top_level.txt
deepqt-1.1.7.dist-info/RECORD
