Metadata-Version: 2.1
Name: deepqt
Version: 1.1.7
Summary: Harness the power of the DeepL API with this friendly user interface.
Home-page: https://github.com/VoxelCubes/DeepQt
Keywords: deepl,deepl api,qt,pyside6
Classifier: Programming Language :: Python :: 3.10
Classifier: License :: OSI Approved :: GNU General Public License v3 or later (GPLv3+)
Classifier: Operating System :: POSIX :: Linux
Classifier: Operating System :: Microsoft :: Windows
Requires-Python: >=3.10
License-File: LICENSE
Requires-Dist: deepl
Requires-Dist: logzero
Requires-Dist: PySide6
Requires-Dist: xdg
Requires-Dist: pyexcel
Requires-Dist: pyexcel-odsr
Requires-Dist: pyexcel-xls
Requires-Dist: pyexcel-xlsx
Requires-Dist: pyexcel-htmlr
Requires-Dist: beautifulsoup4
Requires-Dist: minify-html
Requires-Dist: lxml
